aiopool/base.py
aiopool/fork.py
aiopool/spawn.py
aiopool/__init__.py
aiopool-0.0.2a1.dist-info/METADATA
aiopool-0.0.2a1.dist-info/RECORD
aiopool-0.0.2a1.dist-info/top_level.txt
aiopool-0.0.2a1.dist-info/DESCRIPTION.rst
aiopool-0.0.2a1.dist-info/metadata.json
aiopool-0.0.2a1.dist-info/WHEEL
